kegg_manual/__init__.py
kegg_manual/entry.py
kegg_manual/formula.py
kegg_manual/kmodule.py
kegg_manual/load.py
kegg_manual/utils.py
kegg_manual/data/__init__.py
kegg_manual/data/cache.py
kegg_manual/data/organism
kegg_manual/data/query.py
kegg_manual/data/__pycache__/__init__.cpython-310.pyc
kegg_manual/data/__pycache__/__init__.cpython-312.pyc
kegg_manual/data/__pycache__/cache.cpython-310.pyc
kegg_manual/data/__pycache__/cache.cpython-312.pyc
kegg_manual/data/__pycache__/query.cpython-310.pyc
kegg_manual/data/__pycache__/query.cpython-312.pyc
kegg_manual/data/brite/ko00001.json
kegg_manual/data/brite/ko00002.json
kegg_manual/data/compound/C00001
kegg_manual/data/compound/C02987
kegg_manual/data/ec/2.3.3.1
kegg_manual/data/ec/4.2.1.3
kegg_manual/data/ko/K01647
kegg_manual/data/ko/K01681
kegg_manual/data/manual/module/M00004
kegg_manual/data/manual/module/M00006
kegg_manual/data/manual/module/M00014
kegg_manual/data/manual/module/M00015
kegg_manual/data/manual/module/M00022
kegg_manual/data/manual/module/M00023
kegg_manual/data/manual/module/M00025
kegg_manual/data/manual/module/M00026
kegg_manual/data/manual/module/M00032
kegg_manual/data/manual/module/M00036
kegg_manual/data/manual/module/M00045
kegg_manual/data/manual/module/M00048
kegg_manual/data/manual/module/M00051
kegg_manual/data/manual/module/M00055
kegg_manual/data/manual/module/M00065
kegg_manual/data/manual/module/M00082
kegg_manual/data/manual/module/M00083
kegg_manual/data/manual/module/M00087
kegg_manual/data/manual/module/M00091
kegg_manual/data/manual/module/M00126
kegg_manual/data/manual/module/M00127
kegg_manual/data/manual/module/M00140
kegg_manual/data/manual/module/M00141
kegg_manual/data/manual/module/M00144
kegg_manual/data/manual/module/M00151
kegg_manual/data/manual/module/M00154
kegg_manual/data/manual/module/M00156
kegg_manual/data/manual/module/M00165
kegg_manual/data/manual/module/M00173
kegg_manual/data/manual/module/M00174
kegg_manual/data/manual/module/M00307
kegg_manual-0.0.2.dist-info/METADATA
kegg_manual-0.0.2.dist-info/WHEEL
kegg_manual-0.0.2.dist-info/top_level.txt
kegg_manual-0.0.2.dist-info/RECORD
