Metadata-Version: 2.4
Name: kegg_manual
Version: 0.0.2
Summary: local handler of KEGG data
Author-email: "hwrn.aou" <hwrn.aou@sjtu.edu.cn>
Requires-Python: >=3.11
